pyech/__init__.py
pyech/_version.py
pyech/core.py
pyech/external.py
pyech/utils.py
pyech-0.1.0.dist-info/LICENSE
pyech-0.1.0.dist-info/METADATA
pyech-0.1.0.dist-info/WHEEL
pyech-0.1.0.dist-info/top_level.txt
pyech-0.1.0.dist-info/RECORD
