Metadata-Version: 2.1
Name: pyech
Version: 0.1.0
Summary: Process INE's ECH surveys in Python.
Home-page: https://github.com/cpa-analytics/pyech
Author: CPA Ferrere | Data Analytics
License: MIT
Keywords: uruguay,survey,ech,statistics,ine,data
Platform: UNKNOWN
Classifier: Development Status :: 3 - Alpha
Classifier: Intended Audience :: Science/Research
Classifier: Intended Audience :: End Users/Desktop
Classifier: Intended Audience :: Other Audience
Classifier: Topic :: Sociology
Classifier: License :: OSI Approved :: MIT License
Classifier: Programming Language :: Python
Classifier: Programming Language :: Python :: 3.6
Classifier: Programming Language :: Python :: 3.7
Classifier: Programming Language :: Python :: 3.8
Classifier: Operating System :: OS Independent
Requires-Python: >=3.6
Requires-Dist: pandas (>=1.2.0)
Requires-Dist: patool
Requires-Dist: pyreadstat
Requires-Dist: pandas-weighting
Requires-Dist: openpyxl (>=2.6.0)
Requires-Dist: xlrd (>=1.2.0)
Requires-Dist: tables
